[
    {
        "rel": 1.8076171875,
        "nrel": [
            -1.939453125,
            -1.0927734375,
            -1.5400390625,
            -0.70849609375,
            -0.294677734375,
            -0.4150390625,
            -1.9150390625,
            0.8037109375,
            -0.24609375
        ]
    },
    {
        "rel": 1.087890625,
        "nrel": [
            -0.94970703125,
            -0.685546875,
            -1.1259765625,
            -0.544921875,
            -0.6875,
            -0.81298828125,
            -1.0634765625,
            -0.427978515625,
            -1.29296875
        ]
    },
    {
        "rel": -0.2154541015625,
        "nrel": [
            -0.94970703125,
            -0.685546875,
            -1.1259765625,
            -0.544921875,
            -0.6875,
            -0.81298828125,
            -1.0634765625,
            -0.427978515625,
            -1.29296875
        ]
    },
    {
        "rel": 0.2108154296875,
        "nrel": [
            -1.001953125,
            -0.537109375,
            -1.34375,
            0.397216796875,
            -0.95703125,
            -0.34228515625,
            -1.8828125,
            -0.58447265625,
            -0.2001953125
        ]
    },
    {
        "rel": 0.9541015625,
        "nrel": [
            -1.6669921875,
            0.6513671875,
            -1.7265625,
            -1.396484375,
            -1.439453125,
            0.047821044921875,
            0.64208984375,
            0.11065673828125,
            -1.693359375
        ]
    },
    {
        "rel": 0.0994873046875,
        "nrel": [
            0.54345703125,
            -0.306640625,
            -1.26953125,
            -1.4853515625,
            -0.962890625,
            -1.775390625,
            -0.787109375,
            -0.7626953125,
            -1.337890625
        ]
    },
    {
        "rel": -0.0015306472778320312,
        "nrel": [
            0.257568359375,
            0.040496826171875,
            1.068359375,
            0.71484375,
            -1.6220703125,
            -1.724609375,
            0.09051513671875,
            -1.1826171875,
            -0.62939453125
        ]
    },
    {
        "rel": -0.07879638671875,
        "nrel": [
            -0.59619140625,
            -1.267578125,
            -1.859375,
            -1.1533203125,
            -2.328125,
            -2.603515625,
            -0.6982421875,
            -1.5439453125,
            -0.96826171875
        ]
    },
    {
        "rel": 0.32568359375,
        "nrel": [
            0.69921875,
            0.6435546875,
            -0.9912109375,
            -0.5302734375,
            -0.38720703125,
            0.11712646484375,
            -0.68359375,
            -1.1376953125,
            0.1845703125
        ]
    },
    {
        "rel": 2.076171875,
        "nrel": [
            -1.365234375,
            -0.53271484375,
            -1.728515625,
            -1.185546875,
            -1.0302734375,
            -1.4609375,
            -1.662109375,
            -1.671875,
            -0.66357421875
        ]
    },
    {
        "rel": 2.078125,
        "nrel": [
            -0.445556640625,
            -1.828125,
            -1.3408203125,
            -2.0234375,
            -0.382568359375,
            -0.66552734375,
            -0.87451171875,
            -1.5615234375,
            -0.91552734375
        ]
    },
    {
        "rel": 0.69921875,
        "nrel": [
            -1.0361328125,
            -0.62060546875,
            -0.447021484375,
            -0.75341796875,
            -0.708984375,
            0.79248046875,
            -0.8046875,
            1.095703125,
            0.2626953125
        ]
    },
    {
        "rel": 0.5361328125,
        "nrel": [
            -1.6083984375,
            0.278076171875,
            -0.810546875,
            -0.75927734375,
            0.055908203125,
            0.96044921875,
            -0.70947265625,
            0.17626953125,
            -0.241943359375
        ]
    },
    {
        "rel": 2.6484375,
        "nrel": [
            -0.37109375,
            -1.296875,
            -1.5263671875,
            -2.05078125,
            -0.3212890625,
            -0.57421875,
            0.25146484375,
            -1.4248046875,
            -1.0439453125
        ]
    },
    {
        "rel": 2.533203125,
        "nrel": [
            -0.37109375,
            -1.296875,
            -1.5263671875,
            -2.05078125,
            -0.3212890625,
            -0.57421875,
            0.25146484375,
            -1.4248046875,
            -1.0439453125
        ]
    },
    {
        "rel": 2.283203125,
        "nrel": [
            -0.37109375,
            -1.296875,
            -1.5263671875,
            -2.05078125,
            -0.3212890625,
            -0.57421875,
            0.25146484375,
            -1.4248046875,
            -1.0439453125
        ]
    },
    {
        "rel": -0.425048828125,
        "nrel": [
            -0.79833984375,
            -0.1463623046875,
            -0.0718994140625,
            -0.2205810546875,
            -1.6279296875,
            -0.1640625,
            -0.9150390625,
            -0.576171875,
            -1.44921875
        ]
    },
    {
        "rel": 1.6396484375,
        "nrel": [
            -0.71484375,
            -0.110595703125,
            -0.33349609375,
            -0.0908203125,
            -1.46484375,
            4.8160552978515625e-05,
            -0.33349609375,
            -0.736328125,
            -1.4375
        ]
    },
    {
        "rel": 1.9501953125,
        "nrel": [
            0.6572265625,
            0.423828125,
            -1.1396484375,
            -0.458740234375,
            -0.034912109375,
            -0.96630859375,
            0.345947265625,
            -1.921875,
            0.66650390625
        ]
    },
    {
        "rel": 0.84912109375,
        "nrel": [
            0.1549072265625,
            -1.224609375,
            -0.77392578125,
            0.84326171875,
            -0.822265625,
            0.74365234375,
            -1.0458984375,
            -0.6337890625,
            -1.51953125
        ]
    },
    {
        "rel": -0.83154296875,
        "nrel": [
            -0.473876953125,
            -0.5439453125,
            1.3701171875,
            0.52734375,
            -1.591796875,
            0.1912841796875,
            -0.853515625,
            -1.4013671875,
            -0.38330078125
        ]
    },
    {
        "rel": 0.00687408447265625,
        "nrel": [
            -0.544921875,
            -1.00390625,
            0.08984375,
            -0.28271484375,
            -0.1763916015625,
            -1.5068359375,
            -1.8046875,
            -1.3564453125,
            -0.14990234375
        ]
    },
    {
        "rel": -0.299560546875,
        "nrel": [
            -1.017578125,
            -1.30078125,
            -1.57421875,
            -1.5498046875,
            -0.623046875,
            -0.611328125,
            -1.3740234375,
            0.03521728515625,
            -1.3115234375
        ]
    },
    {
        "rel": 1.1044921875,
        "nrel": [
            -0.65966796875,
            -1.1962890625,
            -0.39892578125,
            -0.1790771484375,
            -0.0850830078125,
            -0.98681640625,
            0.211181640625,
            -1.490234375,
            -1.8017578125
        ]
    },
    {
        "rel": 3.705078125,
        "nrel": [
            0.16064453125,
            -2.765625,
            -1.458984375,
            -2.470703125,
            -1.060546875,
            -1.9873046875,
            -3.388671875,
            -1.3193359375,
            -0.264404296875
        ]
    },
    {
        "rel": 1.357421875,
        "nrel": [
            -1.8701171875,
            -0.07769775390625,
            -0.126708984375,
            -0.318359375,
            -0.378662109375,
            -1.1962890625,
            -1.2080078125,
            -0.650390625,
            -0.8349609375
        ]
    },
    {
        "rel": 1.0615234375,
        "nrel": [
            0.71923828125,
            -0.2734375,
            -0.394775390625,
            -1.36328125,
            -0.3994140625,
            0.3876953125,
            -0.494140625,
            1.099609375,
            -0.623046875
        ]
    },
    {
        "rel": 0.5322265625,
        "nrel": [
            0.59326171875,
            1.0224609375,
            -0.8603515625,
            -0.1934814453125,
            -0.81005859375,
            -0.49951171875,
            -1.505859375,
            -1.98828125,
            -0.8525390625
        ]
    },
    {
        "rel": 1.2900390625,
        "nrel": [
            0.0655517578125,
            -0.7724609375,
            -1.0732421875,
            -0.33935546875,
            0.08160400390625,
            -1.1357421875,
            -1.1494140625,
            -0.276123046875,
            -1.09375
        ]
    },
    {
        "rel": 0.8828125,
        "nrel": [
            -1.498046875,
            -1.783203125,
            -1.45703125,
            -1.017578125,
            -2.732421875,
            -2.4296875,
            -0.67333984375,
            -1.4697265625,
            0.69921875
        ]
    },
    {
        "rel": 2.193359375,
        "nrel": [
            -0.65966796875,
            -1.201171875,
            -1.466796875,
            -0.9501953125,
            -2.1484375,
            0.179443359375,
            -0.28857421875,
            -2.107421875,
            -1.439453125
        ]
    },
    {
        "rel": -0.25439453125,
        "nrel": [
            -1.20703125,
            -1.2109375,
            0.0090484619140625,
            -0.27734375,
            -0.73486328125,
            -0.79833984375,
            -1.103515625,
            -0.28076171875,
            -1.216796875
        ]
    },
    {
        "rel": -0.84033203125,
        "nrel": [
            -0.0251617431640625,
            -1.7880859375,
            -0.96435546875,
            -0.56689453125,
            -1.0771484375,
            -0.329345703125,
            0.56103515625,
            -0.7578125,
            -1.419921875
        ]
    },
    {
        "rel": 1.9013671875,
        "nrel": [
            -0.2578125,
            0.556640625,
            0.1260986328125,
            -1.0546875,
            0.08013916015625,
            -1.314453125,
            -1.017578125,
            -1.1376953125,
            -0.67626953125
        ]
    },
    {
        "rel": 1.078125,
        "nrel": [
            -1.1767578125,
            -1.4326171875,
            -1.5869140625,
            -1.9736328125,
            -1.3896484375,
            -2.228515625,
            -1.6220703125,
            -0.093994140625,
            -1.2373046875
        ]
    },
    {
        "rel": 0.66748046875,
        "nrel": [
            -0.3056640625,
            -0.564453125,
            -2.42578125,
            -2.27734375,
            -1.126953125,
            1.4326171875,
            0.257568359375,
            0.307861328125,
            -1.32421875
        ]
    },
    {
        "rel": 0.274169921875,
        "nrel": [
            -0.3056640625,
            -0.564453125,
            -2.42578125,
            -2.27734375,
            -1.126953125,
            1.4326171875,
            0.257568359375,
            0.307861328125,
            -1.32421875
        ]
    },
    {
        "rel": 1.0615234375,
        "nrel": [
            -0.87890625,
            0.5029296875,
            0.145751953125,
            -1.2353515625,
            -0.50390625,
            -1.041015625,
            0.0428466796875,
            0.232177734375,
            -1.3984375
        ]
    },
    {
        "rel": 0.5068359375,
        "nrel": [
            -0.734375,
            -0.96435546875,
            -0.5166015625,
            -1.466796875,
            0.0004470348358154297,
            -0.70068359375,
            -0.2056884765625,
            -1.4765625,
            0.92724609375
        ]
    },
    {
        "rel": 1.353515625,
        "nrel": [
            -0.037506103515625,
            1.32421875,
            0.382080078125,
            -0.71533203125,
            -0.78564453125,
            -1.4130859375,
            -1.1064453125,
            -1.482421875,
            -0.84228515625
        ]
    },
    {
        "rel": 1.828125,
        "nrel": [
            -1.3779296875,
            0.367431640625,
            -2.208984375,
            -1.5048828125,
            -0.1314697265625,
            -1.564453125,
            -2.2890625,
            -2.478515625,
            -1.431640625
        ]
    },
    {
        "rel": 0.63330078125,
        "nrel": [
            -0.775390625,
            -1.7080078125,
            -1.212890625,
            -1.806640625,
            -0.322509765625,
            -1.5869140625,
            -1.5673828125,
            -0.4736328125,
            -0.89208984375
        ]
    },
    {
        "rel": 1.6181640625,
        "nrel": [
            -1.12890625,
            -1.037109375,
            -0.8974609375,
            -1.748046875,
            -1.865234375,
            -0.57421875,
            -2.1484375,
            -1.69140625,
            -2.375
        ]
    },
    {
        "rel": 0.95703125,
        "nrel": [
            -1.021484375,
            -0.71923828125,
            -0.7001953125,
            -1.4326171875,
            0.1058349609375,
            -0.77880859375,
            0.289794921875,
            -1.640625,
            -1.9013671875
        ]
    },
    {
        "rel": -0.06683349609375,
        "nrel": [
            -0.80615234375,
            -0.294677734375,
            -1.3505859375,
            -1.6826171875,
            0.60546875,
            -1.341796875,
            -1.8955078125,
            0.171875,
            -1.8232421875
        ]
    },
    {
        "rel": 1.0322265625,
        "nrel": [
            1.458984375,
            -1.6884765625,
            -0.76171875,
            -0.88037109375,
            -0.8740234375,
            -0.8291015625,
            -0.349365234375,
            -0.9287109375,
            -0.94873046875
        ]
    },
    {
        "rel": 0.92919921875,
        "nrel": [
            -1.5244140625,
            -0.5576171875,
            -0.515625,
            -2.650390625,
            -0.1334228515625,
            0.1881103515625,
            -0.54248046875,
            -2.14453125,
            0.18115234375
        ]
    },
    {
        "rel": 0.2191162109375,
        "nrel": [
            0.317138671875,
            -1.169921875,
            -0.318359375,
            -1.15234375,
            -2.533203125,
            -1.572265625,
            -1.1337890625,
            -1.6953125,
            0.021392822265625
        ]
    },
    {
        "rel": 2.765625,
        "nrel": [
            -0.333984375,
            -1.083984375,
            -0.491943359375,
            -0.9931640625,
            -1.6123046875,
            -0.95556640625,
            0.32958984375,
            -0.8583984375,
            -0.63427734375
        ]
    },
    {
        "rel": 0.90673828125,
        "nrel": [
            0.07708740234375,
            -1.49609375,
            -0.464111328125,
            0.64599609375,
            0.035003662109375,
            -1.2421875,
            -0.10809326171875,
            -0.422119140625,
            -1.236328125
        ]
    }
]