{
    "Document Tokens Attending Very Rare Lexical Match Query Tokens": -0.5251252347084077,
    "Rare Document Tokens Attending Very Rare Lexical Match Query Tokens": -0.5251252347084077,
    "Very Rare Document Tokens Attending Lexical Match Query Tokens": -0.5251252347084077,
    "Very Rare Document Tokens Attending Very Rare Lexical Match Query Tokens": -0.5251252347084077,
    "Very Rare Document Tokens Attending Rare Lexical Match Query Tokens": -0.5251252347084077,
    "Rare Document Tokens Attending Lexical Match Query Tokens": -0.5195795327823607,
    "Rare Document Tokens Attending Rare Lexical Match Query Tokens": -0.5195795327823607,
    "Document Tokens Attending Rare Lexical Match Query Tokens": -0.5195795327823607,
    "Rare Document Tokens Attending Rare Semantic Match Query Tokens": -0.5120560203069169,
    "Rare Document Tokens Attending Semantic Match Query Tokens": -0.5120379822931884,
    "Document Tokens Attending Rare Semantic Match Query Tokens": -0.5110093161120551,
    "Very Rare Document Tokens Attending Semantic Match Query Tokens": -0.5102953743065219,
    "Very Rare Document Tokens Attending Rare Semantic Match Query Tokens": -0.5101601743165332,
    "Document Tokens Attending Semantic Match Query Tokens": -0.5078569831639641,
    "Document Tokens Attending Very Rare Semantic Match Query Tokens": -0.5075477873628886,
    "Rare Document Tokens Attending Very Rare Semantic Match Query Tokens": -0.5069301787571167,
    "Very Rare Document Tokens Attending Very Rare Semantic Match Query Tokens": -0.4999546396334654,
    "Very Rare Document Tokens Attending Rare Query Tokens": -0.4569051666814593,
    "Very Rare Document Tokens Attending Very Rare Query Tokens": -0.45035698318548945,
    "Rare Document Tokens Attending Rare Query Tokens": -0.4205072185786545,
    "Rare Document Tokens Attending Very Rare Query Tokens": -0.39521502874719794,
    "Document Tokens Attending Lexical Match Query Tokens": -0.3554131203942451,
    "Document Tokens Attending Rare Query Tokens": -0.35198808505717094,
    "All Tokens Attending Lexical Match Tokens": 0.3402217369503963,
    "Document Tokens Attending Lexical Match Document Tokens": 0.3400755162134643,
    "All Tokens Attending Lexical Match Document Tokens": 0.3400755162134643,
    "Query Tokens Attending Very Rare Lexical Match Tokens": 0.33101595117379623,
    "Rare Query Tokens Attending Very Rare Lexical Match Tokens": 0.33101595117379623,
    "Very Rare Query Tokens Attending Lexical Match Query Tokens": 0.33101595117379623,
    "Very Rare Query Tokens Attending Lexical Match Tokens": 0.33101595117379623,
    "Very Rare Query Tokens Attending Very Rare Lexical Match Tokens": 0.33101595117379623,
    "Very Rare Query Tokens Attending Rare Lexical Match Query Tokens": 0.33101595117379623,
    "Very Rare Query Tokens Attending Very Rare Lexical Match Query Tokens": 0.33101595117379623,
    "Very Rare Query Tokens Attending Rare Lexical Match Tokens": 0.33101595117379623,
    "Rare Query Tokens Attending Very Rare Lexical Match Query Tokens": 0.33101595117379623,
    "Query Tokens Attending Very Rare Lexical Match Query Tokens": 0.33101595117379623,
    "Very Rare Tokens Attending All Tokens": 0.32972169375220006,
    "Document Tokens Attending Rare Tokens": -0.32961610843096406,
    "Document Tokens Attending Lexical Match Tokens": 0.32741493700112567,
    "Very Rare Tokens Attending Rare Query Tokens": -0.3214350082973675,
    "All Tokens Attending Rare Tokens": -0.3205334997753049,
    "Rare Tokens Attending Rare Query Tokens": -0.3186234273647873,
    "Document Tokens Attending Rare Document Tokens": -0.3016563218239145,
    "All Tokens Attending Rare Document Tokens": -0.3016563218239145,
    "Very Rare Query Tokens Attending Very Rare Semantic Match Query Tokens": 0.29601889242050256,
    "Very Rare Query Tokens Attending Very Rare Semantic Match Tokens": 0.29601889242050256,
    "All Tokens Attending Rare Query Tokens": -0.29426156184109553,
    "Rare Tokens Attending Very Rare Lexical Match Document Tokens": 0.29241055781344955,
    "Very Rare Document Tokens Attending Rare Lexical Match Document Tokens": 0.29241055781344955,
    "Very Rare Tokens Attending Rare Lexical Match Document Tokens": 0.29241055781344955,
    "Document Tokens Attending Very Rare Lexical Match Document Tokens": 0.29241055781344955,
    "Very Rare Tokens Attending Lexical Match Document Tokens": 0.29241055781344955,
    "All Tokens Attending Very Rare Lexical Match Document Tokens": 0.29241055781344955,
    "Very Rare Document Tokens Attending Lexical Match Document Tokens": 0.29241055781344955,
    "Rare Document Tokens Attending Very Rare Lexical Match Document Tokens": 0.29241055781344955,
    "Very Rare Tokens Attending Very Rare Lexical Match Document Tokens": 0.29241055781344955,
    "Very Rare Document Tokens Attending Very Rare Lexical Match Document Tokens": 0.29241055781344955,
    "Query Tokens Attending Lexical Match Tokens": 0.2921432584783006,
    "Query Tokens Attending Lexical Match Query Tokens": 0.2921432584783006,
    "Very Rare Query Tokens Attending Rare Semantic Match Query Tokens": 0.2888803357432708,
    "Very Rare Query Tokens Attending Rare Semantic Match Tokens": 0.2888803357432708,
    "Rare Query Tokens Attending Lexical Match Query Tokens": 0.28780003666653675,
    "Rare Query Tokens Attending Lexical Match Tokens": 0.28780003666653675,
    "Rare Query Tokens Attending Rare Lexical Match Tokens": 0.28780003666653675,
    "Query Tokens Attending Rare Lexical Match Query Tokens": 0.28780003666653675,
    "Query Tokens Attending Rare Lexical Match Tokens": 0.28780003666653675,
    "Rare Query Tokens Attending Rare Lexical Match Query Tokens": 0.28780003666653675,
    "Very Rare Query Tokens Attending Semantic Match Tokens": 0.286750629888431,
    "Very Rare Query Tokens Attending Semantic Match Query Tokens": 0.286750629888431,
    "Very Rare Document Tokens Attending All Tokens": 0.285837896339767,
    "Rare Query Tokens Attending Very Rare Semantic Match Query Tokens": 0.28295269892351577,
    "Rare Query Tokens Attending Very Rare Semantic Match Tokens": 0.28295269892351577,
    "Query Tokens Attending Very Rare Semantic Match Query Tokens": 0.28242800844665966,
    "Query Tokens Attending Very Rare Semantic Match Tokens": 0.28242800844665966,
    "Document Tokens Attending Very Rare Query Tokens": -0.2789687299538043,
    "Rare Tokens Attending Very Rare Query Tokens": -0.27097565944931123,
    "Rare Document Tokens Attending Rare Tokens": -0.2702877310982961,
    "All Tokens Attending Very Rare Lexical Match Tokens": 0.26700239921921953,
    "Very Rare Tokens Attending Very Rare Lexical Match Tokens": 0.26700239921921953,
    "Very Rare Tokens Attending Rare Lexical Match Tokens": 0.26700239921921953,
    "Very Rare Tokens Attending Lexical Match Tokens": 0.26700239921921953,
    "Rare Tokens Attending Very Rare Lexical Match Tokens": 0.26700239921921953,
    "Very Rare Document Tokens Attending Rare Tokens": -0.2637312411128214,
    "All Tokens Attending Rare Lexical Match Document Tokens": 0.2618724949992155,
    "Rare Tokens Attending Lexical Match Document Tokens": 0.2618724949992155,
    "Rare Document Tokens Attending Lexical Match Document Tokens": 0.2618724949992155,
    "Rare Tokens Attending Rare Lexical Match Document Tokens": 0.2618724949992155,
    "Rare Document Tokens Attending Rare Lexical Match Document Tokens": 0.2618724949992155,
    "Document Tokens Attending Rare Lexical Match Document Tokens": 0.2618724949992155,
    "Rare Tokens Attending Rare Tokens": -0.25321888578134705,
    "Very Rare Document Tokens Attending Very Rare Lexical Match Tokens": 0.24686947112299557,
    "Very Rare Document Tokens Attending Rare Lexical Match Tokens": 0.24686947112299557,
    "Very Rare Document Tokens Attending Lexical Match Tokens": 0.24686947112299557,
    "Rare Document Tokens Attending Very Rare Lexical Match Tokens": 0.24686947112299557,
    "Document Tokens Attending Very Rare Lexical Match Tokens": 0.24686947112299557,
    "Very Rare Tokens Attending Very Rare Query Tokens": -0.24680657945736034,
    "Rare Document Tokens Attending All Tokens": 0.241118238153587,
    "Rare Tokens Attending Rare Lexical Match Tokens": 0.24067400753050072,
    "All Tokens Attending Rare Lexical Match Tokens": 0.24067400753050072,
    "Rare Tokens Attending Lexical Match Tokens": 0.24067400753050072,
    "Rare Tokens Attending All Tokens": 0.24034510818559596,
    "Rare Query Tokens Attending Rare Semantic Match Query Tokens": 0.23973347045261137,
    "Rare Query Tokens Attending Rare Semantic Match Tokens": 0.23973347045261137,
    "Very Rare Tokens Attending Rare Tokens": -0.23972627440953492,
    "Query Tokens Attending Rare Semantic Match Query Tokens": 0.23834132402993097,
    "Query Tokens Attending Rare Semantic Match Tokens": 0.23834132402993097,
    "Rare Query Tokens Attending Semantic Match Tokens": 0.23756215315418483,
    "Rare Query Tokens Attending Semantic Match Query Tokens": 0.23756215315418483,
    "Query Tokens Attending Semantic Match Tokens": 0.23254059739064725,
    "Query Tokens Attending Semantic Match Query Tokens": 0.23254059739064725,
    "Document Tokens Attending Very Rare Tokens": -0.2322812777756606,
    "Rare Document Tokens Attending Lexical Match Tokens": 0.2257550780050861,
    "Document Tokens Attending Rare Lexical Match Tokens": 0.2257550780050861,
    "Rare Document Tokens Attending Rare Lexical Match Tokens": 0.2257550780050861,
    "All Tokens Attending Very Rare Tokens": -0.21998491237180356,
    "Very Rare Query Tokens Attending Very Rare Tokens": 0.2170764078622811,
    "Very Rare Query Tokens Attending Very Rare Query Tokens": 0.2170764078622811,
    "Very Rare Tokens Attending Very Rare Semantic Match Document Tokens": 0.2156945333864731,
    "Very Rare Document Tokens Attending Very Rare Semantic Match Document Tokens": 0.2156945333864731,
    "Rare Tokens Attending Rare Document Tokens": -0.20873771198097102,
    "Rare Document Tokens Attending Rare Document Tokens": -0.20873771198097102,
    "All Tokens Attending Very Rare Query Tokens": -0.208547476397139,
    "Rare Document Tokens Attending Very Rare Tokens": -0.20573171462371154,
    "All Tokens Attending Very Rare Document Tokens": -0.20021937796715933,
    "Document Tokens Attending Very Rare Document Tokens": -0.20021937796715933,
    "Document Tokens Attending Very Rare Semantic Match Document Tokens": 0.19680503302462976,
    "All Tokens Attending Very Rare Semantic Match Document Tokens": 0.19680503302462976,
    "Rare Tokens Attending Very Rare Semantic Match Document Tokens": 0.1964629328377534,
    "Rare Document Tokens Attending Very Rare Semantic Match Document Tokens": 0.1964629328377534,
    "Very Rare Tokens Attending Rare Document Tokens": -0.19403148690018035,
    "Very Rare Document Tokens Attending Rare Document Tokens": -0.19403148690018035,
    "Very Rare Tokens Attending Very Rare Semantic Match Tokens": 0.19378860532431622,
    "Very Rare Document Tokens Attending Rare Semantic Match Document Tokens": 0.18958388544239552,
    "Very Rare Tokens Attending Rare Semantic Match Document Tokens": 0.18958388544239552,
    "Very Rare Document Tokens Attending Document Tokens": 0.18732104838916394,
    "Very Rare Tokens Attending Document Tokens": 0.18732104838916394,
    "Very Rare Document Tokens Attending Semantic Match Document Tokens": 0.18630316942178984,
    "Very Rare Tokens Attending Semantic Match Document Tokens": 0.18630316942178984,
    "Rare Tokens Attending Very Rare Tokens": -0.18393744328147585,
    "Very Rare Document Tokens Attending Very Rare Semantic Match Tokens": 0.17158218694292715,
    "All Tokens Attending Lexical Match Query Tokens": 0.17030778634749996,
    "All Tokens Attending Very Rare Semantic Match Tokens": 0.1701372896122606,
    "Rare Tokens Attending Very Rare Semantic Match Tokens": 0.16996017479891096,
    "Very Rare Tokens Attending Rare Semantic Match Tokens": 0.1637109273270071,
    "Rare Tokens Attending Rare Semantic Match Document Tokens": 0.1625144969875696,
    "Rare Document Tokens Attending Rare Semantic Match Document Tokens": 0.1625144969875696,
    "Very Rare Tokens Attending Semantic Match Tokens": 0.1600602927393754,
    "Document Tokens Attending Rare Semantic Match Document Tokens": 0.15846590207370878,
    "All Tokens Attending Rare Semantic Match Document Tokens": 0.15846590207370878,
    "Rare Document Tokens Attending Semantic Match Document Tokens": 0.15585602421946534,
    "Rare Tokens Attending Semantic Match Document Tokens": 0.15585602421946534,
    "All Tokens Attending Semantic Match Document Tokens": 0.15457410208019073,
    "Document Tokens Attending Semantic Match Document Tokens": 0.15457410208019073,
    "Document Tokens Attending Very Rare Semantic Match Tokens": 0.14665839137960068,
    "Rare Document Tokens Attending Very Rare Semantic Match Tokens": 0.1465468669991249,
    "Rare Tokens Attending Document Tokens": 0.1458596409961679,
    "Rare Document Tokens Attending Document Tokens": 0.1458596409961679,
    "Very Rare Document Tokens Attending Rare Semantic Match Tokens": 0.1387107978181021,
    "Rare Tokens Attending Rare Semantic Match Tokens": 0.13661495377819602,
    "Very Rare Document Tokens Attending Semantic Match Tokens": 0.135017018350351,
    "Rare Document Tokens Attending Very Rare Document Tokens": -0.13324450875631647,
    "Rare Tokens Attending Very Rare Document Tokens": -0.13324450875631647,
    "Very Rare Document Tokens Attending Very Rare Tokens": -0.1328858185649575,
    "All Tokens Attending Rare Semantic Match Tokens": 0.13233502498456792,
    "All Tokens Attending Semantic Match Tokens": 0.1305012911161871,
    "Rare Tokens Attending Semantic Match Tokens": 0.12975989762085147,
    "Very Rare Document Tokens Attending Query Tokens": -0.12090677005140979,
    "Rare Query Tokens Attending Very Rare Query Tokens": 0.11956122389472351,
    "Rare Query Tokens Attending Very Rare Tokens": 0.11956122389472351,
    "Very Rare Query Tokens Attending Rare Query Tokens": 0.11721299203035357,
    "Very Rare Query Tokens Attending Rare Tokens": 0.11721299203035357,
    "Rare Document Tokens Attending Rare Semantic Match Tokens": 0.11679415206785326,
    "Document Tokens Attending Rare Semantic Match Tokens": 0.11208553622734233,
    "Document Tokens Attending Semantic Match Tokens": 0.11167259542873903,
    "Rare Document Tokens Attending Semantic Match Tokens": 0.1094649581122647,
    "Rare Document Tokens Attending Query Tokens": -0.10685896380379008,
    "Very Rare Tokens Attending Very Rare Tokens": -0.10044419898621826,
    "Rare Tokens Attending Semantic Match Query Tokens": -0.08602504532100023,
    "All Tokens Attending Rare Semantic Match Query Tokens": -0.08493847812715673,
    "Rare Tokens Attending Rare Semantic Match Query Tokens": -0.08114191186372405,
    "All Tokens Attending Semantic Match Query Tokens": -0.08024972914075437,
    "Very Rare Query Tokens Attending All Tokens": 0.07666407831256507,
    "Very Rare Query Tokens Attending Query Tokens": 0.07666407831256507,
    "Document Tokens Attending Query Tokens": -0.07180505111228035,
    "Very Rare Tokens Attending Semantic Match Query Tokens": -0.06500236526805808,
    "Rare Tokens Attending Query Tokens": -0.06416480985213646,
    "All Tokens Attending Very Rare Semantic Match Query Tokens": -0.06294155948331617,
    "Rare Tokens Attending Very Rare Semantic Match Query Tokens": -0.06136122395176625,
    "Very Rare Tokens Attending Rare Semantic Match Query Tokens": -0.06091271731721561,
    "Query Tokens Attending Very Rare Query Tokens": 0.05838287151055922,
    "Query Tokens Attending Very Rare Tokens": 0.05838287151055922,
    "Very Rare Tokens Attending Query Tokens": -0.05763624508813878,
    "Very Rare Document Tokens Attending Very Rare Document Tokens": -0.04827450060421515,
    "Very Rare Tokens Attending Very Rare Document Tokens": -0.04827450060421515,
    "Document Tokens Attending All Tokens": -0.04714420590972401,
    "Query Tokens Attending All Tokens": 0.047109794247602484,
    "Query Tokens Attending Query Tokens": 0.047109794247602484,
    "Query Tokens Attending Rare Query Tokens": -0.04588443838059359,
    "Query Tokens Attending Rare Tokens": -0.04588443838059359,
    "Rare Query Tokens Attending Query Tokens": 0.041636657549476194,
    "Rare Query Tokens Attending All Tokens": 0.041636657549476194,
    "Rare Query Tokens Attending Rare Tokens": 0.0395804121162216,
    "Rare Query Tokens Attending Rare Query Tokens": 0.0395804121162216,
    "All Tokens Attending Query Tokens": -0.036080680199615335,
    "All Tokens Attending Document Tokens": 0.03607789179180876,
    "Document Tokens Attending Document Tokens": 0.03607789179180876,
    "Very Rare Tokens Attending Very Rare Semantic Match Query Tokens": -0.021115211392319894,
    "Rare Tokens Attending Lexical Match Query Tokens": 0.020514316477002387,
    "All Tokens Attending Rare Lexical Match Query Tokens": 0.020514316477002387,
    "Rare Tokens Attending Rare Lexical Match Query Tokens": 0.020514316477002387,
    "Very Rare Tokens Attending Lexical Match Query Tokens": 0.011294968751264706,
    "All Tokens Attending Very Rare Lexical Match Query Tokens": 0.011294968751264706,
    "Very Rare Tokens Attending Very Rare Lexical Match Query Tokens": 0.011294968751264706,
    "Very Rare Tokens Attending Rare Lexical Match Query Tokens": 0.011294968751264706,
    "Rare Tokens Attending Very Rare Lexical Match Query Tokens": 0.011294968751264706
}